codegen/__init__.py
codegen/models/__init__.py
codegen/models/ast.py
codegen/models/expr.py
codegen/models/program.py
codegen/models/statement.py
codegen/models/types.py
codegen/models/var.py
codegen_2-2.15.6.dist-info/METADATA
codegen_2-2.15.6.dist-info/WHEEL
codegen_2-2.15.6.dist-info/licenses/LICENSE
codegen_2-2.15.6.dist-info/RECORD
