Metadata-Version: 2.4
Name: codegen-2
Version: 2.15.6
Summary: Meta-programming
License: MIT
License-File: LICENSE
Author: Binh Vu
Author-email: binh@toan2.com
Requires-Python: >=3.11,<4.0
Classifier: License :: OSI Approved :: MIT License
Classifier: Programming Language :: Python :: 3
Classifier: Programming Language :: Python :: 3.11
Classifier: Programming Language :: Python :: 3.12
Classifier: Programming Language :: Python :: 3.13
Classifier: Programming Language :: Python :: 3.14
